scrape_721/__init__.py
scrape_721/__main__.py
scrape_721/constants.py
scrape_721/contract_utils.py
scrape_721/main.py
scrape_721-0.3.0.dist-info/entry_points.txt
scrape_721-0.3.0.dist-info/LICENSE
scrape_721-0.3.0.dist-info/WHEEL
scrape_721-0.3.0.dist-info/METADATA
scrape_721-0.3.0.dist-info/RECORD
